langtools/core/__init__.py
langtools/core/credential.py
langtools/core/logger.py
langtools/core/meter.py
langtools/core/tracer.py
langtools/core/exporters/__init__.py
langtools/core/exporters/azure_monitor.py
langtools/core/exporters/console_exporter.py
langtools/core/exporters/file_exporter.py
langtools/core/exporters/noop_exporter.py
langtools/core/identity/LongRunningOBOTokenCredential.py
langtools/core/identity/__init__.py
langtools/core/utils/openai_result_parser.py
langtools/core/utils/serializer.py
langtools_core-0.1.0b2.dist-info/METADATA
langtools_core-0.1.0b2.dist-info/WHEEL
langtools_core-0.1.0b2.dist-info/top_level.txt
langtools_core-0.1.0b2.dist-info/RECORD
