Metadata-Version: 2.4
Name: langtools-core
Version: 0.1.0b2
Summary: Core functionality for language tools
Author-email: MSAI Team <langtoolsdev@microsoft.com>
Project-URL: Homepage, https://github.com/ai-microsoft/langtools
Project-URL: Issues, https://github.com/ai-microsoft/langtools/issues
Classifier: Programming Language :: Python :: 3
Classifier: License :: OSI Approved :: MIT License
Classifier: Operating System :: OS Independent
Requires-Python: >=3.8
Requires-Dist: opentelemetry-sdk>=1.30.0
Requires-Dist: opentelemetry-api>=1.30.0
Requires-Dist: azure-monitor-opentelemetry-exporter>=1.0.0b33
Requires-Dist: azure-identity>=1.17.0
Requires-Dist: azure-core>=1.17.0
Requires-Dist: azure-keyvault-secrets>=4.7.0
Requires-Dist: pydantic>=2.7.4
Requires-Dist: orjson>=3.9.10
Requires-Dist: tiktoken>=0.5.2
Requires-Dist: openai>=1.0.0
Requires-Dist: python-dotenv>=1.0.0
